{
	"SubTitle" : "Ponte en la ranura",
	"Information" : "Similar a las medidas y tiempos, el ritmo es acerca de acentos y cómo se siente la música. Sin embargo, donde las medidas simplemente te dice cuántos latidos, el ritmo te dice como se utilizan. Pruebe esto: toque el dedo en su escritorio y contar 1-2-3-4 1-2-3-4, constantemente. No es muy interesante, ¿verdad? Ahora intenta esto: en 1 y 3, toque más fuerte y en 2 y 4, más suave. Tiene un toque diferente. Ahora prueba lo contrario: golpear fuerte en 2 y 4 y suave en 1 y 3. Usted comenzará a tener una idea de cómo se organiza la música. Eso es lo que llamamos ritmo!",
	"NextLessonFile" : "3.2.json",
	"PreviousLessonFile" : "2.1.json",
	"Descriptions" : [
		{
			"Image" : "ms-appx:///Media/Images/QuarterNotes.png"	
		}
	]
}